simpel_contacts/__init__.py
simpel_contacts/abstracts.py
simpel_contacts/admin.py
simpel_contacts/apps.py
simpel_contacts/forms.py
simpel_contacts/models.py
simpel_contacts/settings.py
simpel_contacts/urls.py
simpel_contacts/version.py
simpel_contacts/api/__init__.py
simpel_contacts/api/serializers.py
simpel_contacts/api/views.py
simpel_contacts/api/viewsets.py
simpel_contacts/management/__init__.py
simpel_contacts/management/commands/__init__.py
simpel_contacts/management/commands/populate_countries.py
simpel_contacts/migrations/0001_initial.py
simpel_contacts/migrations/0002_remove_linkedaddress_zipcode.py
simpel_contacts/migrations/0003_auto_20220324_1858.py
simpel_contacts/migrations/0004_auto_20220327_2358.py
simpel_contacts/migrations/0005_auto_20220328_0249.py
simpel_contacts/migrations/0006_auto_20220328_0255.py
simpel_contacts/migrations/0007_billingaddress_deliverableaddress_shippingaddress.py
simpel_contacts/migrations/0008_auto_20220420_0929.py
simpel_contacts/migrations/0009_auto_20220420_1548.py
simpel_contacts/migrations/__init__.py
simpel_contacts/templates/admin/simpel_contacts/.gitinclude
simpel_contacts/templates/simpel_contacts/.gitinclude
simpel_contacts/tests/__init__.py
simpel_contacts/tests/tests_models.py
simpel_contacts-0.1.8.dist-info/LICENSE
simpel_contacts-0.1.8.dist-info/METADATA
simpel_contacts-0.1.8.dist-info/WHEEL
simpel_contacts-0.1.8.dist-info/top_level.txt
simpel_contacts-0.1.8.dist-info/RECORD
